owega/__init__.py
owega/__main__.py
owega/ask.py
owega/colors.py
owega/constants.py
owega/getLogger.py
owega/handlerBase.py
owega/license.py
owega/owega.py
owega/pricing.py
owega/utils.py
owega/OweHandlers/__init__.py
owega/OweHandlers/handle_add_sysmem.py
owega/OweHandlers/handle_commands.py
owega/OweHandlers/handle_context.py
owega/OweHandlers/handle_del_sysmem.py
owega/OweHandlers/handle_dinput.py
owega/OweHandlers/handle_edit.py
owega/OweHandlers/handle_estimation.py
owega/OweHandlers/handle_fancy.py
owega/OweHandlers/handle_finput.py
owega/OweHandlers/handle_frequency.py
owega/OweHandlers/handle_genconf.py
owega/OweHandlers/handle_history.py
owega/OweHandlers/handle_image.py
owega/OweHandlers/handle_load.py
owega/OweHandlers/handle_lts.py
owega/OweHandlers/handle_model.py
owega/OweHandlers/handle_presence.py
owega/OweHandlers/handle_quit.py
owega/OweHandlers/handle_reprint.py
owega/OweHandlers/handle_save.py
owega/OweHandlers/handle_system.py
owega/OweHandlers/handle_temperature.py
owega/OweHandlers/handle_time.py
owega/OweHandlers/handle_tokens.py
owega/OweHandlers/handle_top_p.py
owega/OweHandlers/handle_tts.py
owega/OweHandlers/handle_web.py
owega/OweHandlers/handlers.py
owega/OweHandlers/helpers.py
owega/OwegaFun/__init__.py
owega/OwegaFun/functions.py
owega/OwegaFun/imageGen.py
owega/OwegaFun/longTermSouvenirs.py
owega/OwegaFun/utility.py
owega/OwegaSession/__init__.py
owega/OwegaSession/main_bottom_toolbar.py
owega/OwegaSession/promptsession.py
owega/changelog/__init__.py
owega/changelog/changelog.py
owega/changelog/changelogEntry.py
owega/changelog/version.py
owega/config/__init__.py
owega/config/baseConfSource.py
owega/conversation/__init__.py
owega/conversation/conversation.py
owega-5.27.1.dist-info/licenses/LICENSE
owega-5.27.1.dist-info/METADATA
owega-5.27.1.dist-info/WHEEL
owega-5.27.1.dist-info/entry_points.txt
owega-5.27.1.dist-info/top_level.txt
owega-5.27.1.dist-info/RECORD
