Metadata-Version: 2.4
Name: owega
Version: 5.27.1
Summary: A command-line interface for conversing with AI APIs (OpenAI, anthropic, ...)
Author-email: darkgeem <darkgeem@pyrokinesis.fr>
License-Expression: LicenseRef-DGPL-1.0
Project-URL: Source, https://git.pyrokinesis.fr/darkgeem/owega
Project-URL: Support, https://discord.gg/KdRmyRrA48
Classifier: Development Status :: 5 - Production/Stable
Classifier: Environment :: Console
Classifier: Intended Audience :: Developers
Classifier: Intended Audience :: Education
Classifier: Intended Audience :: Information Technology
Classifier: Intended Audience :: Science/Research
Classifier: Intended Audience :: System Administrators
Classifier: Natural Language :: English
Classifier: Operating System :: OS Independent
Classifier: Topic :: File Formats :: JSON
Classifier: Topic :: Multimedia :: Sound/Audio :: Speech
Classifier: Topic :: Scientific/Engineering :: Artificial Intelligence
Requires-Python: >=3.7
License-File: LICENSE
Requires-Dist: openai>=1.45.0
Requires-Dist: prompt_toolkit>=3.0
Requires-Dist: requests>=2.0
Requires-Dist: beautifulsoup4>=4.0
Requires-Dist: json5>=0.9.0
Requires-Dist: python-editor>=1.0.4
Requires-Dist: setuptools>=60.0
Dynamic: license-file
